genesynth/__init__.py
genesynth/cli.py
genesynth/constraints.py
genesynth/graph.py
genesynth/io.py
genesynth/mat.py
genesynth/model.py
genesynth/orchestration.py
genesynth/server.py
genesynth/types.py
genesynth/utils.py
genesynth/version.py
genesynth/vis.py
genesynth/worker.py
genesynth/extensions/__init__.py
genesynth/extensions/llm.py
tests/__init__.py
tests/test_cli.py
tests/test_graph.py
tests/test_io.py
tests/test_mat.py
tests/test_model.py
tests/test_orchestration.py
tests/test_types.py
tests/test_utils.py
tests/test_worker.py
genesynth-0.6.4.dist-info/LICENSE
genesynth-0.6.4.dist-info/METADATA
genesynth-0.6.4.dist-info/WHEEL
genesynth-0.6.4.dist-info/top_level.txt
genesynth-0.6.4.dist-info/RECORD
