Metadata-Version: 2.1
Name: genesynth
Version: 0.6.4
Summary: Python package: genesynth
Author: Gang Huang
License: MIT
Requires-Python: >=3.9
License-File: LICENSE
Requires-Dist: async-generator>=1.10
Requires-Dist: asyncstdlib>=3.10.8
Requires-Dist: Cython>=3.0.0
Requires-Dist: future==0.18.3
Requires-Dist: matplotlib>=3.7.2
Requires-Dist: pandas>=2.0.3
Requires-Dist: networkx>=3.1
Requires-Dist: numpy>=1.22.4
Requires-Dist: pydot==1.4.2
Requires-Dist: pytz==2022.1
Requires-Dist: PyYAML==6.0.1
Requires-Dist: scipy>=1.10.1
Requires-Dist: typing-inspect>=0.9.0
Requires-Dist: typing_extensions>=4.7.1
Requires-Dist: uvloop>=0.17.0
Requires-Dist: mimesis==6.1.1
Requires-Dist: pyvis>=0.3.1
Requires-Dist: fastapi>=0.97.0
Requires-Dist: uvicorn[standard]>=0.23.2
Requires-Dist: httpx>=0.24.0
Requires-Dist: openai>=1.13.3
Requires-Dist: ollama>=0.1.7
Requires-Dist: mergedeep>=1.3.4
